{
  "b": 209,
  "disableInputWhenNotFocused": true,
  "mangledName": "concert",
  "name": "concert",
  "r": 209,
  "standardSortMethod": true,
  "stopSoundsOnStartup": true,
  "title": "",
  "v": 209,
  "uiSettings": {
    "grid": false,
    "gridType": "rectangular",
    "gridWidth": 32,
    "gridHeight": 32,
    "gridOffsetX": 0,
    "gridOffsetY": 0,
    "gridColor": 10401023,
    "gridAlpha": 0.8,
    "snap": false,
    "zoomFactor": 0.546875,
    "windowMask": false
  },
  "objectsGroups": [],
  "variables": [],
  "instances": [
    {
      "angle": 0,
      "customSize": false,
      "height": 0,
      "layer": "",
      "name": "SmallPlasticGreenRoundSlider",
      "persistentUuid": "2a8029a5-2091-4262-8999-ec6bd2af9ba2",
      "width": 0,
      "x": 377,
      "y": 506,
      "zOrder": 1,
      "numberProperties": [],
      "stringProperties": [],
      "initialVariables": []
    },
    {
      "angle": 0,
      "customSize": false,
      "height": 0,
      "layer": "",
      "name": "controleur_audio",
      "persistentUuid": "cdbc5192-5150-4ff7-a011-1f534bcece41",
      "width": 0,
      "x": 1116,
      "y": 90,
      "zOrder": 2,
      "numberProperties": [],
      "stringProperties": [],
      "initialVariables": []
    }
  ],
  "objects": [
    {
      "assetStoreId": "",
      "name": "controleur_audio",
      "tags": "",
      "type": "Sprite",
      "updateIfNotVisible": false,
      "variables": [
        {
          "folded": true,
          "name": "alto",
          "type": "number",
          "value": 0
        },
        {
          "folded": true,
          "name": "flute",
          "type": "number",
          "value": 1
        },
        {
          "folded": true,
          "name": "pont_vent",
          "type": "number",
          "value": 10
        },
        {
          "folded": true,
          "name": "pont_cordes",
          "type": "number",
          "value": 11
        },
        {
          "folded": true,
          "name": "etape",
          "type": "number",
          "value": 1
        }
      ],
      "effects": [],
      "behaviors": [],
      "animations": []
    },
    {
      "assetStoreId": "05b0eb2d13ff37b70927d0184d4705e9c39c0b8fece7463127c4fe9eb65bb422",
      "name": "SmallPlasticGreenRoundSlider",
      "tags": "",
      "type": "PanelSpriteSlider::PanelSpriteSlider",
      "variables": [],
      "effects": [],
      "behaviors": [],
      "content": {
        "LabelMargin": 8,
        "BarLeftPadding": 31,
        "BarRightPadding": 31
      },
      "childrenContent": {
        "Background": {
          "bottomMargin": 31,
          "height": 63,
          "leftMargin": 31,
          "rightMargin": 31,
          "texture": "Small Plastic Green Round Slider Border.png",
          "tiled": false,
          "topMargin": 31,
          "width": 583
        },
        "FillBar": {
          "bottomMargin": 0,
          "height": 16,
          "leftMargin": 0,
          "rightMargin": 0,
          "texture": "Transparent.png",
          "tiled": false,
          "topMargin": 0,
          "width": 16
        },
        "Label": {
          "bold": false,
          "italic": false,
          "smoothed": true,
          "underlined": false,
          "string": "It displays the value when it changes.",
          "font": "",
          "textAlignment": "",
          "characterSize": 20,
          "color": {
            "b": 221,
            "g": 221,
            "r": 221
          }
        },
        "Thumb": {
          "bottomMargin": 0,
          "height": 59,
          "leftMargin": 0,
          "rightMargin": 0,
          "texture": "Small Plastic Green Round Slider Thumb.png",
          "tiled": false,
          "topMargin": 0,
          "width": 63
        }
      }
    },
    {
      "assetStoreId": "4656edcabf61f71dfd0368d92d077267a0dbfeef35ce002d4cb8774906099c57",
      "name": "PlayButton",
      "tags": "",
      "type": "Sprite",
      "updateIfNotVisible": false,
      "variables": [],
      "effects": [],
      "behaviors": [],
      "animations": [
        {
          "name": "",
          "useMultipleDirections": false,
          "directions": [
            {
              "looping": true,
              "timeBetweenFrames": 0.025,
              "sprites": [
                {
                  "hasCustomCollisionMask": false,
                  "image": "Play button.png",
                  "points": [],
                  "originPoint": {
                    "name": "origine",
                    "x": 0,
                    "y": 0
                  },
                  "centerPoint": {
                    "automatic": true,
                    "name": "centre",
                    "x": 0,
                    "y": 0
                  },
                  "customCollisionMask": []
                }
              ]
            }
          ]
        }
      ]
    }
  ],
  "events": [
    {
      "type": "BuiltinCommonInstructions::Standard",
      "conditions": [
        {
          "type": {
            "value": "VarGlobalTxt"
          },
          "parameters": [
            "theme_b.selection",
            "=",
            "\"poule\""
          ]
        }
      ],
      "actions": [],
      "events": [
        {
          "type": "BuiltinCommonInstructions::Standard",
          "conditions": [],
          "actions": [
            {
              "type": {
                "value": "References::CreateGlobalReference"
              },
              "parameters": [
                "",
                "instr_theme_b",
                "theme_b.instruments",
                ""
              ]
            }
          ]
        },
        {
          "type": "BuiltinCommonInstructions::ForEachChildVariable",
          "iterableVariableName": "instr_theme_b",
          "valueIteratorVariableName": "instr",
          "keyIteratorVariableName": "",
          "conditions": [],
          "actions": [],
          "events": [
            {
              "type": "BuiltinCommonInstructions::Standard",
              "conditions": [
                {
                  "type": {
                    "value": "VarSceneTxt"
                  },
                  "parameters": [
                    "instr",
                    "=",
                    "\"alto\""
                  ]
                }
              ],
              "actions": [
                {
                  "type": {
                    "value": "PlaySoundCanal"
                  },
                  "parameters": [
                    "",
                    "25 Alto.mp3",
                    "controleur_audio.Variable(alto)",
                    "100",
                    "100",
                    "1"
                  ]
                }
              ]
            },
            {
              "type": "BuiltinCommonInstructions::Standard",
              "conditions": [
                {
                  "type": {
                    "value": "VarSceneTxt"
                  },
                  "parameters": [
                    "instr",
                    "=",
                    "\"flute\""
                  ]
                }
              ],
              "actions": [
                {
                  "type": {
                    "value": "PlaySoundCanal"
                  },
                  "parameters": [
                    "",
                    "25 Flute.mp3",
                    "controleur_audio.Variable(flute)",
                    "100",
                    "100",
                    "1"
                  ]
                }
              ]
            }
          ]
        },
        {
          "type": "BuiltinCommonInstructions::Standard",
          "conditions": [],
          "actions": [
            {
              "type": {
                "value": "References::CreateGlobalReference"
              },
              "parameters": [
                "",
                "instr_accompagnement_b",
                "theme_b.instruments",
                ""
              ]
            }
          ]
        }
      ]
    },
    {
      "type": "BuiltinCommonInstructions::Standard",
      "conditions": [],
      "actions": [
        {
          "type": {
            "value": "ModVolumeSoundCanal"
          },
          "parameters": [
            "",
            "controleur_audio.Variable(alto)",
            "=",
            "SmallPlasticGreenRoundSlider.Value()"
          ]
        },
        {
          "type": {
            "value": "ModVolumeSoundCanal"
          },
          "parameters": [
            "",
            "controleur_audio.Variable(flute)",
            "=",
            "SmallPlasticGreenRoundSlider.Value()"
          ]
        }
      ]
    },
    {
      "type": "BuiltinCommonInstructions::Standard",
      "conditions": [],
      "actions": []
    },
    {
      "type": "BuiltinCommonInstructions::Standard",
      "conditions": [
        {
          "type": {
            "value": "DepartScene"
          },
          "parameters": [
            ""
          ]
        }
      ],
      "actions": [
        {
          "type": {
            "value": "BuiltinExternalLayouts::CreateObjectsFromExternalLayout"
          },
          "parameters": [
            "",
            "\"ticket\"",
            "0",
            "0"
          ]
        }
      ]
    }
  ],
  "layers": [
    {
      "ambientLightColorB": 7719864,
      "ambientLightColorG": 150995054,
      "ambientLightColorR": 1869182049,
      "followBaseLayerCamera": false,
      "isLightingLayer": false,
      "name": "",
      "visibility": true,
      "cameras": [
        {
          "defaultSize": true,
          "defaultViewport": true,
          "height": 0,
          "viewportBottom": 1,
          "viewportLeft": 0,
          "viewportRight": 1,
          "viewportTop": 0,
          "width": 0
        }
      ],
      "effects": []
    },
    {
      "ambientLightColorB": 28,
      "ambientLightColorG": 6069792,
      "ambientLightColorR": 10000008,
      "followBaseLayerCamera": false,
      "isLightingLayer": false,
      "name": "bg selection",
      "visibility": true,
      "cameras": [],
      "effects": []
    },
    {
      "ambientLightColorB": 28,
      "ambientLightColorG": 6069792,
      "ambientLightColorR": 10000008,
      "followBaseLayerCamera": false,
      "isLightingLayer": false,
      "name": "boutons slection",
      "visibility": true,
      "cameras": [],
      "effects": []
    }
  ],
  "behaviorsSharedData": []
}